Workbook
Name Done_Apr: #REF!
Name Done_Aug: #REF!
Name Done_Dec: #REF!
Name Done_Feb: #REF!
Name Done_Jan: #REF!
Name Done_Jul: #REF!
Name Done_Jun: #REF!
Name Done_Mar: #REF!
Name Done_May: #REF!
Name Done_Nov: #REF!
Name Done_Oct: #REF!
Name Done_Sep: #REF!
Name 完了: #REF!,#REF!,#REF!,#REF!,#REF!,#REF!,#REF!,#REF!,#REF!,#REF!,#REF!,#REF!

Sheet （様式３）支出計画書
B2: 第３回公募 小規模事業者持続化補助金＜共同・協業型＞ | H2: （様式３）
B3: 支出計画書
C5: 申請事業者名 | G5: =IF(D5="","←直接入力","") -> ←直接入力
C6: 経理処理 | G6: =IF(D6="","←プルダウンから選択","") -> ←プルダウンから選択 | I6: ←次に該当しない者は、補助対象経費を「税抜価格」で記載し、上記経理処欄で「税別」を選択。
C7: 取組 | I7: ① 消費税法における納税義務者とならない者
C8: 展示会・商談会の取組 | D8: 催事販売の取組 | F8: 販売拠点構築の取組 | I8: ② 免税事業者、簡易課税事業者及び二割特例
G9: ←複数選択可(プルダウンから選択） | I9: ③ 消費税法別表第三に掲げる法人
I10: ④ 課税事業者のうち課税売上割合が低い等の理由から、消費税仕入控除税額確定後の返還を選択する者
C11: 取組別の参画事業者数 | G11: ←様式2-2(参画事業者一覧)から人数を転記してください。
C12: 展示会・商談会の取組 | D12: 催事販売の取組 | F12: 販売拠点構築の取組
G13: ←全ての事業者数を転記
G14: ←参画事業者の要件を満たす事業者数を転記
C15: =IF(C9<>"✓",IF(C14<>"","↑取組未選択:人数入力あり",""),IF(AND(C9="✓",C14<>""),IF(ISNUMBER(C14),IF(C13<C14,"↑全ての事業者数＜参画事業者の要件を満たす事業者数",""),"↑数値以外を入力"),"↑参画事業者の要件を満たす事業者数：未入力")) | D15: =IF(D9<>"✓",IF(D14<>"","↑取組未選択:人数入力あり",""),IF(AND(D9="✓",D14<>""),IF(ISNUMBER(D14),IF(D13<D14,"↑全ての事業者数＜参画事業者の要件を満たす事業者数",""),"↑数値以外を入力"),"↑参画事業者の要件を満たす事業者数：未入力")) | F15: =IF(F9<>"✓",IF(F14<>"","↑取組未選択:人数入力あり",""),IF(AND(F9="✓",F14<>""),IF(ISNUMBER(F14),IF(F13<F14,"↑全ての事業者数＜参画事業者の要件を満たす事業者数",""),"↑数値以外を入力"),"↑参画事業者の要件を満たす事業者数：未入力"))
C17: 全取組のうち最小の参画事業者数 | D17: =_xlfn.MINIFS(C14:F14,C14:F14,"<>0") -> 0 | F17: 人
C18: 補助上限額 | D18: =IF(_xlfn.MINIFS(C14:F14,C14:F14,"<>0")<5,0,IF(10<=_xlfn.MINIFS(C14:F14,C14:F14,"<>0"),3000,2000)) -> 0 | F18: 万円
C19: ※ 補助上限額
C20: 全ての取組の参画事業者が 10 者以上：3,000 万円
C21: 全ての取組の参画事業者が 5 者以上 9 者以下：2,000 万円
B24: 1. | C24: 経費配分内訳 | H24: （単位：円） | K24: ⑩委託・外注費の上限判定
B25: 経費区分及び明細 | D25: 補助率 | E25: 補助事業に要する経費 Ⓒ | F25: 補助対象 経費 | G25: 補助金要望額 Ⓐ | H25: 自己負担 Ⓑ | I25: =IF((F28+F29+F30++F31+F33)>0,"","※定額補助率 経費のみの計上は認められない。") -> ※定額補助率 経費のみの計上は認められない。 | J25: (ⅰ) | K25: 定額【①、②、⑦、⑨、➉】の合計額 | N25: ％
B26: ①謝金 | D26: 定額 | E26: ='（別添）積算明細書'!H67 -> 0 | F26: =E26 -> 0 | G26: =F26 -> 0 | H26: =E26-G26 -> 0 | I26: =IF(F26<=0,"",IF(F26=INT(F26),"","「補助対象経費」を整数に修正")) | K26: =SUM(G26:G27,G32,G34,G35) -> 0 | M26: ① | N26: =IF(G26=0,"",G26/$G$37)
B27: ②地域振興等機関旅費 | D27: 定額 | E27: ='（別添）積算明細書'!H98 -> 0 | F27: =E27 -> 0 | G27: =F27 -> 0 | H27: =E27-G27 -> 0 | I27: =IF(F27<=0,"",IF(F27=INT(F27),"","「補助対象経費」を整数に修正")) | J27: (ⅱ) | K27: ①、②、⑦、⑨、➉の合計額の1/2 | M27: ② | N27: =IF(G27=0,"",G27/$G$37)
B28: ③参画事業者旅費 | D28: 0.66666667 | E28: ='（別添）積算明細書'!H129 -> 0 | F28: =E28 -> 0 | G28: =ROUNDDOWN(F28*2/3,0) -> 0 | H28: =E28-G28 -> 0 | I28: =IF(F28<=0,"",IF(F28=INT(F28),"","「補助対象経費」を整数に修正")) | K28: =ROUNDDOWN(K26/2,0) -> 0 | M28: ③ | N28: =IF(G28=0,"",G28/$G$37)
B29: ④借料 | D29: 0.66666667 | E29: ='（別添）積算明細書'!H160 -> 0 | F29: =E29 -> 0 | G29: =ROUNDDOWN(F29*2/3,0) -> 0 | H29: =E29-G29 -> 0 | I29: =IF(F29<=0,"",IF(F29=INT(F29),"","「補助対象経費」を整数に修正")) | J29: (ⅲ) | K29: ➉と「①、②、⑦、⑨」の差額 | M29: ④ | N29: =IF(G29=0,"",G29/$G$37)
B30: ⑤設営・設計費 | D30: 0.66666667 | E30: ='（別添）積算明細書'!H221 -> 0 | F30: =E30 -> 0 | G30: =ROUNDDOWN(F30*2/3,0) -> 0 | H30: =E30-G30 -> 0 | I30: =IF(F30<=0,"",IF(F30=INT(F30),"","「補助対象経費」を整数に修正")) | K30: =F35-SUM(F26:F27,F32,F34) -> 0 | M30: ⑤ | N30: =IF(G30=0,"",G30/$G$37)
B31: ⑥展示会等出展費 | D31: 0.66666667 | E31: =IF(AND(C9<>"✓",D9<>"✓",F9="✓"),0,'（別添）積算明細書'!H252) -> 0 | F31: =E31 -> 0 | G31: =IF(AND(C9<>"✓",D9<>"✓",F9="✓"),0,ROUNDDOWN(F31*2/3,0)) -> 0 | H31: =E31-G31 -> 0 | I31: =IF(F31<=0,"",IF(F31=INT(F31),"","「補助対象経費」を整数に修正")) | J31: (ⅳ) | K31: 判定 | M31: ⑥ | N31: =IF(G31=0,"",G31/$G$37)
B32: ⑦備品費 | D32: 定額 | E32: ='（別添）積算明細書'!H283 -> 0 | F32: =E32 -> 0 | G32: =F32 -> 0 | H32: =E32-G32 -> 0 | I32: =IF(F32<=0,"",IF(F32=INT(F32),"","「補助対象経費」を整数に修正")) | K32: =IF(K28<F35,"×","○") -> ○ | M32: ⑦ | N32: =IF(G32=0,"",G32/$G$37)
B33: ⑧広報費 | D33: 0.66666667 | E33: ='（別添）積算明細書'!H314 -> 0 | F33: =E33 -> 0 | G33: =ROUNDDOWN(F33*2/3,0) -> 0 | H33: =E33-G33 -> 0 | I33: =IF(F33<=0,"",IF(F33=INT(F33),"","「補助対象経費」を整数に修正")) | K33: ※ ×は1/2まで減額調整 | M33: ⑧ | N33: =IF(G33=0,"",G33/$G$37)
B34: ⑨印刷製本費 | D34: 定額 | E34: ='（別添）積算明細書'!H345 -> 0 | F34: =E34 -> 0 | G34: =F34 -> 0 | H34: =E34-G34 -> 0 | I34: =IF(F34<=0,"",IF(F34=INT(F34),"","「補助対象経費」を整数に修正")) | M34: ⑨ | N34: =IF(G34=0,"",G34/$G$37)
B35: ⑩委託・外注費 | D35: 定額 | E35: ='（別添）積算明細書'!H446 -> 0 | F35: =E35 -> 0 | G35: =MIN(F35,F35-K30) -> 0 | H35: =E35-G35 -> 0 | I35: =IF(F35<=0,"",IF(F35=INT(F35),IF(K28<F35,"※ ⑩委託・外注費の上限は経費区分「①、②、⑦、⑨、➉」の合計額の1/2以内に減額調整",""),"「補助対象経費」を整数に修正")) | K35: 補助金要望額の上限判定 | M35: ⑩ | N35: =IF(G35=0,"",G35/$G$37)
B36: その他に要する経費 | E36: ='（別添）積算明細書'!H477 -> 0 | H36: =E36 -> 0 | J36: (a) | K36: ①～➉の合計額 | N36: =SUM(N26:N35) -> 0
B37: 合 計 | E37: =SUM(E26:E36) -> 0 | F37: =SUM(F26:F35) -> 0 | G37: =MIN(SUM(G26:G35),D18*10000) -> 0 | H37: =SUM(H26:H36) -> 0 | I37: =IF(D18*10000<SUM(G26:G35),"※「補助金要望額Ⓐ」が上限額を超えています。1申請者1公募回につき"&D18&"万円に減額調整。","") | K37: =SUM(G26:G35) -> 0
B38: ※円未満は切り捨て。 | J38: (ⅱ) | K38: 上限額の超過
B39: ※⑩委託・外注費の上限は経費区分①、②、⑦、⑨、➉の合計額の1/2以内 | K39: =IF(0<SUM(G26:G35)-D18*10000,SUM(G26:G35)-D18*10000,0) -> 0
K40: 判定
K41: =IF(D18*10000<SUM(G26:G35),"×","○") -> ○
B45: 2. | C45: 資金調達内訳 | K45: ※ ×は補助上限額まで減額調整
B46: 区 分 | E46: 金額(円) | G46: 資金の調達先
B47: Ⓐ | C47: 補助金要望額 | E47: =G37 -> 0
B48: Ⓑ | C48: 自己資金
C49: 借入金 | K49: Ⓒと（Ⓐ＋Ⓑ）の差額
C50: その他 | K50: =E37-SUM(E47:F50) -> 0
B51: Ⓒ | C51: 補助事業に要する経費 | E51: =SUM(E47:E50) -> 0 | G51: 上記1.経費配分内訳のⒶ＋Ⓑ＝Ⓒと同額になる | I51: ←1.経費配分内訳の「補助事業に要する経費」と不一致の場合、赤色でエラーが表示される。
B53: 3. | C53: 「2.Ⓐ補助金要望額」の手当方法
B54: 区分 | E54: 金額(円) | G54: 資金の調達先
B55: 自己資金
B56: 借入金 | K56: Ⓐと手当方法の合計金額の差額
B57: その他 | K57: =G37-SUM(E55:F57) -> 0
B58: 補助金要望額 | E58: =SUM(E55:E57) -> 0 | G58: 上記2.資金調達内訳のⒶと同額になる | I58: ←2.資金調達内訳の「Ⓐ補助金要望額」と不一致の場合、赤色でエラーが表示される。

Sheet （別添）積算明細書
B1: 第３回公募 小規模事業者持続化補助金＜共同・協業型＞ | N1: （様式３）支出計画書 別添
B2: 積算明細書 | N2: 申請事業者名： | O2: ='（様式３）支出計画書'!D5 -> 0
B3: ※ どの取組に係る経費か経費別(明細別)に選択する。取組は右記のとおりに略す：展示会・商談会の取組→展、催事販売の取組→催、販売拠点構築の取組→販
B4: ※ 複数の取組にまたがって発生し、単独の取組に直接紐づけられない経費の場合は、複数の取組を選択する。 | N4: 【見積】○：必須、△：代理店に発注する場合は交付申請時に見積書の提出が必須、－：任意
B5: 経費区分 | C5: 明細 番号 | D5: 見積 | E5: 取組 ※ | H5: 計 | I5: 単価 | J5: 数量 | K5: (単位) | L5: 回数等 | M5: (単位) | N5: 内訳の内容 | O5: イベント名 | P5: イベント開催予定月 | Q5: 現時点で発注を予定している取引先候補
E6: 展 | F6: 催 | G6: 販 | U6: ←全ての経費を入力した後、「計」の数値フィルターで「0」のチェックを外すと計上する経費のみが表示されます。(行の削除は禁止)
B7: ①謝金 | C7: 1 | D7: ○ | H7: =IF(L7<=0,I7*J7,I7*J7*L7) -> 0
B8: ①謝金 | C8: =C7+1 -> 2 | D8: ○ | H8: =IF(L8<=0,I8*J8,I8*J8*L8) -> 0
B9: ①謝金 | C9: =C8+1 -> 3 | D9: ○ | H9: =IF(L9<=0,I9*J9,I9*J9*L9) -> 0
B10: ①謝金 | C10: =C9+1 -> 4 | D10: ○ | H10: =IF(L10<=0,I10*J10,I10*J10*L10) -> 0
B11: ①謝金 | C11: =C10+1 -> 5 | D11: ○ | H11: =IF(L11<=0,I11*J11,I11*J11*L11) -> 0
B12: ①謝金 | C12: =C11+1 -> 6 | D12: ○ | H12: =IF(L12<=0,I12*J12,I12*J12*L12) -> 0
B13: ①謝金 | C13: =C12+1 -> 7 | D13: ○ | H13: =IF(L13<=0,I13*J13,I13*J13*L13) -> 0
B14: ①謝金 | C14: =C13+1 -> 8 | D14: ○ | H14: =IF(L14<=0,I14*J14,I14*J14*L14) -> 0
B15: ①謝金 | C15: =C14+1 -> 9 | D15: ○ | H15: =IF(L15<=0,I15*J15,I15*J15*L15) -> 0
B16: ①謝金 | C16: =C15+1 -> 10 | D16: ○ | H16: =IF(L16<=0,I16*J16,I16*J16*L16) -> 0
B17: ①謝金 | C17: =C16+1 -> 11 | D17: ○ | H17: =IF(L17<=0,I17*J17,I17*J17*L17) -> 0
B18: ①謝金 | C18: =C17+1 -> 12 | D18: ○ | H18: =IF(L18<=0,I18*J18,I18*J18*L18) -> 0
B19: ①謝金 | C19: =C18+1 -> 13 | D19: ○ | H19: =IF(L19<=0,I19*J19,I19*J19*L19) -> 0
... B35: ①謝金 | C35: =C34+1 -> 29 | D35: ○ | H35: =IF(L35<=0,I35*J35,I35*J35*L35) -> 0
B36: ①謝金 | C36: =C35+1 -> 30 | D36: ○ | H36: =IF(L36<=0,I36*J36,I36*J36*L36) -> 0 | U36: ↓30行分を非表示にしています。使用する場合は再表示してください。
B37: ①謝金 | C37: =C36+1 -> 31 | D37: ○ | H37: =IF(L37<=0,I37*J37,I37*J37*L37) -> 0
B38: ①謝金 | C38: =C37+1 -> 32 | D38: ○ | H38: =IF(L38<=0,I38*J38,I38*J38*L38) -> 0
B39: ①謝金 | C39: =C38+1 -> 33 | D39: ○ | H39: =IF(L39<=0,I39*J39,I39*J39*L39) -> 0
B40: ①謝金 | C40: =C39+1 -> 34 | D40: ○ | H40: =IF(L40<=0,I40*J40,I40*J40*L40) -> 0
B41: ①謝金 | C41: =C40+1 -> 35 | D41: ○ | H41: =IF(L41<=0,I41*J41,I41*J41*L41) -> 0
B42: ①謝金 | C42: =C41+1 -> 36 | D42: ○ | H42: =IF(L42<=0,I42*J42,I42*J42*L42) -> 0
B43: ①謝金 | C43: =C42+1 -> 37 | D43: ○ | H43: =IF(L43<=0,I43*J43,I43*J43*L43) -> 0
B44: ①謝金 | C44: =C43+1 -> 38 | D44: ○ | H44: =IF(L44<=0,I44*J44,I44*J44*L44) -> 0
B45: ①謝金 | C45: =C44+1 -> 39 | D45: ○ | H45: =IF(L45<=0,I45*J45,I45*J45*L45) -> 0
B46: ①謝金 | C46: =C45+1 -> 40 | D46: ○ | H46: =IF(L46<=0,I46*J46,I46*J46*L46) -> 0
B47: ①謝金 | C47: =C46+1 -> 41 | D47: ○ | H47: =IF(L47<=0,I47*J47,I47*J47*L47) -> 0
B48: ①謝金 | C48: =C47+1 -> 42 | D48: ○ | H48: =IF(L48<=0,I48*J48,I48*J48*L48) -> 0
... B66: ①謝金 | C66: =C65+1 -> 60 | D66: ○ | H66: =IF(L66<=0,I66*J66,I66*J66*L66) -> 0
B67: 合計 | H67: =SUM(H7:H66) -> 0
B68: ②地域振興等機関旅費 | C68: 1 | D68: △ | H68: =IF(L68<=0,I68*J68,I68*J68*L68) -> 0
B69: ②地域振興等機関旅費 | C69: =C68+1 -> 2 | D69: △ | H69: =IF(L69<=0,I69*J69,I69*J69*L69) -> 0
B70: ②地域振興等機関旅費 | C70: =C69+1 -> 3 | D70: △ | H70: =IF(L70<=0,I70*J70,I70*J70*L70) -> 0
B71: ②地域振興等機関旅費 | C71: =C70+1 -> 4 | D71: △ | H71: =IF(L71<=0,I71*J71,I71*J71*L71) -> 0
B72: ②地域振興等機関旅費 | C72: =C71+1 -> 5 | D72: △ | H72: =IF(L72<=0,I72*J72,I72*J72*L72) -> 0
B73: ②地域振興等機関旅費 | C73: =C72+1 -> 6 | D73: △ | H73: =IF(L73<=0,I73*J73,I73*J73*L73) -> 0
B74: ②地域振興等機関旅費 | C74: =C73+1 -> 7 | D74: △ | H74: =IF(L74<=0,I74*J74,I74*J74*L74) -> 0
B75: ②地域振興等機関旅費 | C75: =C74+1 -> 8 | D75: △ | H75: =IF(L75<=0,I75*J75,I75*J75*L75) -> 0
B76: ②地域振興等機関旅費 | C76: =C75+1 -> 9 | D76: △ | H76: =IF(L76<=0,I76*J76,I76*J76*L76) -> 0
B77: ②地域振興等機関旅費 | C77: =C76+1 -> 10 | D77: △ | H77: =IF(L77<=0,I77*J77,I77*J77*L77) -> 0
B78: ②地域振興等機関旅費 | C78: =C77+1 -> 11 | D78: △ | H78: =IF(L78<=0,I78*J78,I78*J78*L78) -> 0
B79: ②地域振興等機関旅費 | C79: =C78+1 -> 12 | D79: △ | H79: =IF(L79<=0,I79*J79,I79*J79*L79) -> 0
B80: ②地域振興等機関旅費 | C80: =C79+1 -> 13 | D80: △ | H80: =IF(L80<=0,I80*J80,I80*J80*L80) -> 0
... B97: ②地域振興等機関旅費 | C97: =C96+1 -> 30 | D97: △ | H97: =IF(L97<=0,I97*J97,I97*J97*L97) -> 0
B98: 合計 | H98: =SUM(H68:H97) -> 0
B99: ③参画事業者旅費 | C99: 1 | D99: △ | H99: =IF(L99<=0,I99*J99,I99*J99*L99) -> 0
B100: ③参画事業者旅費 | C100: =C99+1 -> 2 | D100: △ | H100: =IF(L100<=0,I100*J100,I100*J100*L100) -> 0
B101: ③参画事業者旅費 | C101: =C100+1 -> 3 | D101: △ | H101: =IF(L101<=0,I101*J101,I101*J101*L101) -> 0
B102: ③参画事業者旅費 | C102: =C101+1 -> 4 | D102: △ | H102: =IF(L102<=0,I102*J102,I102*J102*L102) -> 0
B103: ③参画事業者旅費 | C103: =C102+1 -> 5 | D103: △ | H103: =IF(L103<=0,I103*J103,I103*J103*L103) -> 0
B104: ③参画事業者旅費 | C104: =C103+1 -> 6 | D104: △ | H104: =IF(L104<=0,I104*J104,I104*J104*L104) -> 0
B105: ③参画事業者旅費 | C105: =C104+1 -> 7 | D105: △ | H105: =IF(L105<=0,I105*J105,I105*J105*L105) -> 0
B106: ③参画事業者旅費 | C106: =C105+1 -> 8 | D106: △ | H106: =IF(L106<=0,I106*J106,I106*J106*L106) -> 0
B107: ③参画事業者旅費 | C107: =C106+1 -> 9 | D107: △ | H107: =IF(L107<=0,I107*J107,I107*J107*L107) -> 0
B108: ③参画事業者旅費 | C108: =C107+1 -> 10 | D108: △ | H108: =IF(L108<=0,I108*J108,I108*J108*L108) -> 0
B109: ③参画事業者旅費 | C109: =C108+1 -> 11 | D109: △ | H109: =IF(L109<=0,I109*J109,I109*J109*L109) -> 0
B110: ③参画事業者旅費 | C110: =C109+1 -> 12 | D110: △ | H110: =IF(L110<=0,I110*J110,I110*J110*L110) -> 0
B111: ③参画事業者旅費 | C111: =C110+1 -> 13 | D111: △ | H111: =IF(L111<=0,I111*J111,I111*J111*L111) -> 0
... B128: ③参画事業者旅費 | C128: =C127+1 -> 30 | D128: △ | H128: =IF(L128<=0,I128*J128,I128*J128*L128) -> 0
B129: 合計 | H129: =SUM(H99:H128) -> 0
B130: ④借料 | C130: 1 | D130: ○ | H130: =IF(L130<=0,I130*J130,I130*J130*L130) -> 0
B131: ④借料 | C131: =C130+1 -> 2 | D131: ○ | H131: =IF(L131<=0,I131*J131,I131*J131*L131) -> 0
B132: ④借料 | C132: =C131+1 -> 3 | D132: ○ | H132: =IF(L132<=0,I132*J132,I132*J132*L132) -> 0
B133: ④借料 | C133: =C132+1 -> 4 | D133: ○ | H133: =IF(L133<=0,I133*J133,I133*J133*L133) -> 0
B134: ④借料 | C134: =C133+1 -> 5 | D134: ○ | H134: =IF(L134<=0,I134*J134,I134*J134*L134) -> 0
B135: ④借料 | C135: =C134+1 -> 6 | D135: ○ | H135: =IF(L135<=0,I135*J135,I135*J135*L135) -> 0
B136: ④借料 | C136: =C135+1 -> 7 | D136: ○ | H136: =IF(L136<=0,I136*J136,I136*J136*L136) -> 0
B137: ④借料 | C137: =C136+1 -> 8 | D137: ○ | H137: =IF(L137<=0,I137*J137,I137*J137*L137) -> 0
B138: ④借料 | C138: =C137+1 -> 9 | D138: ○ | H138: =IF(L138<=0,I138*J138,I138*J138*L138) -> 0
B139: ④借料 | C139: =C138+1 -> 10 | D139: ○ | H139: =IF(L139<=0,I139*J139,I139*J139*L139) -> 0
B140: ④借料 | C140: =C139+1 -> 11 | D140: ○ | H140: =IF(L140<=0,I140*J140,I140*J140*L140) -> 0
B141: ④借料 | C141: =C140+1 -> 12 | D141: ○ | H141: =IF(L141<=0,I141*J141,I141*J141*L141) -> 0
B142: ④借料 | C142: =C141+1 -> 13 | D142: ○ | H142: =IF(L142<=0,I142*J142,I142*J142*L142) -> 0
... B159: ④借料 | C159: =C158+1 -> 30 | D159: ○ | H159: =IF(L159<=0,I159*J159,I159*J159*L159) -> 0
B160: 合計 | H160: =SUM(H130:H159) -> 0
B161: ⑤設営・設計費 （内外装費、整備工事等を含む） | C161: 1 | D161: ○ | H161: =IF(L161<=0,I161*J161,I161*J161*L161) -> 0
B162: ⑤設営・設計費 （内外装費、整備工事等を含む） | C162: =C161+1 -> 2 | D162: ○ | H162: =IF(L162<=0,I162*J162,I162*J162*L162) -> 0
B163: ⑤設営・設計費 （内外装費、整備工事等を含む） | C163: =C162+1 -> 3 | D163: ○ | H163: =IF(L163<=0,I163*J163,I163*J163*L163) -> 0
B164: ⑤設営・設計費 （内外装費、整備工事等を含む） | C164: =C163+1 -> 4 | D164: ○ | H164: =IF(L164<=0,I164*J164,I164*J164*L164) -> 0
B165: ⑤設営・設計費 （内外装費、整備工事等を含む） | C165: =C164+1 -> 5 | D165: ○ | H165: =IF(L165<=0,I165*J165,I165*J165*L165) -> 0
B166: ⑤設営・設計費 （内外装費、整備工事等を含む） | C166: =C165+1 -> 6 | D166: ○ | H166: =IF(L166<=0,I166*J166,I166*J166*L166) -> 0
B167: ⑤設営・設計費 （内外装費、整備工事等を含む） | C167: =C166+1 -> 7 | D167: ○ | H167: =IF(L167<=0,I167*J167,I167*J167*L167) -> 0
B168: ⑤設営・設計費 （内外装費、整備工事等を含む） | C168: =C167+1 -> 8 | D168: ○ | H168: =IF(L168<=0,I168*J168,I168*J168*L168) -> 0
B169: ⑤設営・設計費 （内外装費、整備工事等を含む） | C169: =C168+1 -> 9 | D169: ○ | H169: =IF(L169<=0,I169*J169,I169*J169*L169) -> 0
B170: ⑤設営・設計費 （内外装費、整備工事等を含む） | C170: =C169+1 -> 10 | D170: ○ | H170: =IF(L170<=0,I170*J170,I170*J170*L170) -> 0
B171: ⑤設営・設計費 （内外装費、整備工事等を含む） | C171: =C170+1 -> 11 | D171: ○ | H171: =IF(L171<=0,I171*J171,I171*J171*L171) -> 0
B172: ⑤設営・設計費 （内外装費、整備工事等を含む） | C172: =C171+1 -> 12 | D172: ○ | H172: =IF(L172<=0,I172*J172,I172*J172*L172) -> 0
B173: ⑤設営・設計費 （内外装費、整備工事等を含む） | C173: =C172+1 -> 13 | D173: ○ | H173: =IF(L173<=0,I173*J173,I173*J173*L173) -> 0
... B189: ⑤設営・設計費 （内外装費、整備工事等を含む） | C189: =C188+1 -> 29 | D189: ○ | H189: =IF(L189<=0,I189*J189,I189*J189*L189) -> 0
B190: ⑤設営・設計費 （内外装費、整備工事等を含む） | C190: =C189+1 -> 30 | D190: ○ | H190: =IF(L190<=0,I190*J190,I190*J190*L190) -> 0 | U190: ↓30行分を非表示にしています。使用する場合は再表示してください。
B191: ⑤設営・設計費 （内外装費、整備工事等を含む） | C191: =C190+1 -> 31 | D191: ○ | H191: =IF(L191<=0,I191*J191,I191*J191*L191) -> 0
B192: ⑤設営・設計費 （内外装費、整備工事等を含む） | C192: =C191+1 -> 32 | D192: ○ | H192: =IF(L192<=0,I192*J192,I192*J192*L192) -> 0
B193: ⑤設営・設計費 （内外装費、整備工事等を含む） | C193: =C192+1 -> 33 | D193: ○ | H193: =IF(L193<=0,I193*J193,I193*J193*L193) -> 0
B194: ⑤設営・設計費 （内外装費、整備工事等を含む） | C194: =C193+1 -> 34 | D194: ○ | H194: =IF(L194<=0,I194*J194,I194*J194*L194) -> 0
B195: ⑤設営・設計費 （内外装費、整備工事等を含む） | C195: =C194+1 -> 35 | D195: ○ | H195: =IF(L195<=0,I195*J195,I195*J195*L195) -> 0
...

Sheet リスト
A1: 展示・商談会
A2: 催事販売
A3: マーケティング拠点

Sheet （別添）積算明細書 (記入例)
B1: 第３回公募 小規模事業者持続化補助金＜共同・協業型＞ | N1: （様式３）支出計画書 別添
B2: 積算明細書 | N2: 申請事業者名： | O2: ='（様式３）支出計画書'!D5 -> 0
B3: ※ どの取組に係る経費か経費別(明細別)に選択する。取組は右記のとおりに略す：展示会・商談会の取組→展、催事販売の取組→催、販売拠点構築の取組→販
B4: ※ 複数の取組にまたがって発生し、単独の取組に直接紐づけられない経費の場合は、複数の取組を選択する。 | N4: 【見積】○：必須、△：代理店に発注する場合は交付申請時に見積書の提出が必須、－：任意
B5: 経費区分 | C5: 明細 番号 | D5: 見積 | E5: 取組 ※ | H5: 計 | I5: 単価 | J5: 数量 | K5: (単位) | L5: 回数等 | M5: (単位) | N5: 内訳の内容 | O5: イベント名 | P5: イベント開催予定月 | Q5: 現時点で発注を予定している取引先候補
E6: 展 | F6: 催 | G6: 販 | U6: ←全ての経費を入力した後、「計」の数値フィルターで「0」のチェックを外すと計上する経費のみが表示されます。(行の削除は禁止)
B7: ①謝金 | C7: 1 | D7: ○ | E7: ✓ | F7: ✓ | G7: ✓ | H7: =IF(L7<=0,I7*J7,I7*J7*L7) -> 168000 | I7: 7000 | J7: 24 | L7: 1 | M7: 人 | N7: ☆☆物産展の事前指導セミナー講師料(参画事業者向け) （８時間×３日間＝２４時間） 謝金の単価は「別添2（区分⓺、民間：課長級）」を根拠とする | P7: １０月、１１月、１２月 | Q7: 株式会社××パートナー
B8: ①謝金 | C8: =C7+1 -> 2 | D8: ○ | H8: =IF(L8<=0,I8*J8,I8*J8*L8) -> 0
B9: ①謝金 | C9: =C8+1 -> 3 | D9: ○ | H9: =IF(L9<=0,I9*J9,I9*J9*L9) -> 0
B10: ①謝金 | C10: =C9+1 -> 4 | D10: ○ | H10: =IF(L10<=0,I10*J10,I10*J10*L10) -> 0
B11: ①謝金 | C11: =C10+1 -> 5 | D11: ○ | H11: =IF(L11<=0,I11*J11,I11*J11*L11) -> 0
B12: ①謝金 | C12: =C11+1 -> 6 | D12: ○ | H12: =IF(L12<=0,I12*J12,I12*J12*L12) -> 0
B13: ①謝金 | C13: =C12+1 -> 7 | D13: ○ | H13: =IF(L13<=0,I13*J13,I13*J13*L13) -> 0
B14: ①謝金 | C14: =C13+1 -> 8 | D14: ○ | H14: =IF(L14<=0,I14*J14,I14*J14*L14) -> 0
B15: ①謝金 | C15: =C14+1 -> 9 | D15: ○ | H15: =IF(L15<=0,I15*J15,I15*J15*L15) -> 0
B16: ①謝金 | C16: =C15+1 -> 10 | D16: ○ | H16: =IF(L16<=0,I16*J16,I16*J16*L16) -> 0
B17: ①謝金 | C17: =C16+1 -> 11 | D17: ○ | H17: =IF(L17<=0,I17*J17,I17*J17*L17) -> 0
B18: ①謝金 | C18: =C17+1 -> 12 | D18: ○ | H18: =IF(L18<=0,I18*J18,I18*J18*L18) -> 0
B19: ①謝金 | C19: =C18+1 -> 13 | D19: ○ | H19: =IF(L19<=0,I19*J19,I19*J19*L19) -> 0
... B35: ①謝金 | C35: =C34+1 -> 29 | D35: ○ | H35: =IF(L35<=0,I35*J35,I35*J35*L35) -> 0
B36: ①謝金 | C36: =C35+1 -> 30 | D36: ○ | H36: =IF(L36<=0,I36*J36,I36*J36*L36) -> 0 | U36: ↓30行分を非表示にしています。使用する場合は再表示してください。
B37: ①謝金 | C37: =C36+1 -> 31 | D37: ○ | H37: =IF(L37<=0,I37*J37,I37*J37*L37) -> 0
B38: ①謝金 | C38: =C37+1 -> 32 | D38: ○ | H38: =IF(L38<=0,I38*J38,I38*J38*L38) -> 0
B39: ①謝金 | C39: =C38+1 -> 33 | D39: ○ | H39: =IF(L39<=0,I39*J39,I39*J39*L39) -> 0
B40: ①謝金 | C40: =C39+1 -> 34 | D40: ○ | H40: =IF(L40<=0,I40*J40,I40*J40*L40) -> 0
B41: ①謝金 | C41: =C40+1 -> 35 | D41: ○ | H41: =IF(L41<=0,I41*J41,I41*J41*L41) -> 0
B42: ①謝金 | C42: =C41+1 -> 36 | D42: ○ | H42: =IF(L42<=0,I42*J42,I42*J42*L42) -> 0
B43: ①謝金 | C43: =C42+1 -> 37 | D43: ○ | H43: =IF(L43<=0,I43*J43,I43*J43*L43) -> 0
B44: ①謝金 | C44: =C43+1 -> 38 | D44: ○ | H44: =IF(L44<=0,I44*J44,I44*J44*L44) -> 0
B45: ①謝金 | C45: =C44+1 -> 39 | D45: ○ | H45: =IF(L45<=0,I45*J45,I45*J45*L45) -> 0
B46: ①謝金 | C46: =C45+1 -> 40 | D46: ○ | H46: =IF(L46<=0,I46*J46,I46*J46*L46) -> 0
B47: ①謝金 | C47: =C46+1 -> 41 | D47: ○ | H47: =IF(L47<=0,I47*J47,I47*J47*L47) -> 0
B48: ①謝金 | C48: =C47+1 -> 42 | D48: ○ | H48: =IF(L48<=0,I48*J48,I48*J48*L48) -> 0
... B66: ①謝金 | C66: =C65+1 -> 60 | D66: ○ | H66: =IF(L66<=0,I66*J66,I66*J66*L66) -> 0
B67: 合計 | H67: =SUM(H7:H66) -> 168000
B68: ②地域振興等機関旅費 | C68: 1 | D68: △ | H68: =IF(L68<=0,I68*J68,I68*J68*L68) -> 400000 | I68: 200000 | J68: 2 | K68: 人 | N68: ○○展示会の指揮責任者（補助事業者） 飛行機(航空券)：成田空港⇒ロサンゼルス国際空港(往復)×２人、宿泊：米国(ロサンゼル）3日×２人 | O68: ○○展示会 | P68: 10月 | Q68: 株式会社○○トラベル
B69: ②地域振興等機関旅費 | C69: =C68+1 -> 2 | D69: △ | H69: =IF(L69<=0,I69*J69,I69*J69*L69) -> 0
B70: ②地域振興等機関旅費 | C70: =C69+1 -> 3 | D70: △ | H70: =IF(L70<=0,I70*J70,I70*J70*L70) -> 0
B71: ②地域振興等機関旅費 | C71: =C70+1 -> 4 | D71: △ | H71: =IF(L71<=0,I71*J71,I71*J71*L71) -> 0
B72: ②地域振興等機関旅費 | C72: =C71+1 -> 5 | D72: △ | H72: =IF(L72<=0,I72*J72,I72*J72*L72) -> 0
B73: ②地域振興等機関旅費 | C73: =C72+1 -> 6 | D73: △ | H73: =IF(L73<=0,I73*J73,I73*J73*L73) -> 0
B74: ②地域振興等機関旅費 | C74: =C73+1 -> 7 | D74: △ | H74: =IF(L74<=0,I74*J74,I74*J74*L74) -> 0
B75: ②地域振興等機関旅費 | C75: =C74+1 -> 8 | D75: △ | H75: =IF(L75<=0,I75*J75,I75*J75*L75) -> 0
B76: ②地域振興等機関旅費 | C76: =C75+1 -> 9 | D76: △ | H76: =IF(L76<=0,I76*J76,I76*J76*L76) -> 0
B77: ②地域振興等機関旅費 | C77: =C76+1 -> 10 | D77: △ | H77: =IF(L77<=0,I77*J77,I77*J77*L77) -> 0
B78: ②地域振興等機関旅費 | C78: =C77+1 -> 11 | D78: △ | H78: =IF(L78<=0,I78*J78,I78*J78*L78) -> 0
B79: ②地域振興等機関旅費 | C79: =C78+1 -> 12 | D79: △ | H79: =IF(L79<=0,I79*J79,I79*J79*L79) -> 0
B80: ②地域振興等機関旅費 | C80: =C79+1 -> 13 | D80: △ | H80: =IF(L80<=0,I80*J80,I80*J80*L80) -> 0
... B97: ②地域振興等機関旅費 | C97: =C96+1 -> 30 | D97: △ | H97: =IF(L97<=0,I97*J97,I97*J97*L97) -> 0
B98: 合計 | H98: =SUM(H68:H97) -> 400000
B99: ③参画事業者旅費 | C99: 1 | D99: △ | H99: =IF(L99<=0,I99*J99,I99*J99*L99) -> 220000 | I99: 22000 | J99: 10 | K99: 人 | N99: イベント出店参加旅費（交通費） 電車：名古屋駅⇔東京駅（往復） ※ １１，０００円×２(往復）×１０人 | O99: ○○展示会 | P99: 10月 | Q99: ●●旅客鉄道株式会社
B100: ③参画事業者旅費 | C100: =C99+1 -> 2 | D100: △ | H100: =IF(L100<=0,I100*J100,I100*J100*L100) -> 1498000 | I100: 21400 | J100: 10 | K100: 人 | L100: 7 | M100: 日 | N100: イベント出店参加旅費（宿泊費） 宿泊：東京都（１９，０００円×7日×１０人） 宿泊手当：２，４００円×（7日×１０人） | O100: ☆☆物産展 | P100: 11月 | Q100: ■■ホテル
B101: ③参画事業者旅費 | C101: =C100+1 -> 3 | D101: △ | H101: =IF(L101<=0,I101*J101,I101*J101*L101) -> 0
B102: ③参画事業者旅費 | C102: =C101+1 -> 4 | D102: △ | H102: =IF(L102<=0,I102*J102,I102*J102*L102) -> 0
B103: ③参画事業者旅費 | C103: =C102+1 -> 5 | D103: △ | H103: =IF(L103<=0,I103*J103,I103*J103*L103) -> 0
B104: ③参画事業者旅費 | C104: =C103+1 -> 6 | D104: △ | H104: =IF(L104<=0,I104*J104,I104*J104*L104) -> 0
B105: ③参画事業者旅費 | C105: =C104+1 -> 7 | D105: △ | H105: =IF(L105<=0,I105*J105,I105*J105*L105) -> 0
B106: ③参画事業者旅費 | C106: =C105+1 -> 8 | D106: △ | H106: =IF(L106<=0,I106*J106,I106*J106*L106) -> 0
B107: ③参画事業者旅費 | C107: =C106+1 -> 9 | D107: △ | H107: =IF(L107<=0,I107*J107,I107*J107*L107) -> 0
B108: ③参画事業者旅費 | C108: =C107+1 -> 10 | D108: △ | H108: =IF(L108<=0,I108*J108,I108*J108*L108) -> 0
B109: ③参画事業者旅費 | C109: =C108+1 -> 11 | D109: △ | H109: =IF(L109<=0,I109*J109,I109*J109*L109) -> 0
B110: ③参画事業者旅費 | C110: =C109+1 -> 12 | D110: △ | H110: =IF(L110<=0,I110*J110,I110*J110*L110) -> 0
B111: ③参画事業者旅費 | C111: =C110+1 -> 13 | D111: △ | H111: =IF(L111<=0,I111*J111,I111*J111*L111) -> 0
B112: ③参画事業者旅費 | C112: =C111+1 -> 14 | D112: △ | H112: =IF(L112<=0,I112*J112,I112*J112*L112) -> 0
... B128: ③参画事業者旅費 | C128: =C127+1 -> 30 | D128: △ | H128: =IF(L128<=0,I128*J128,I128*J128*L128) -> 0
B129: 合計 | H129: =SUM(H99:H128) -> 1718000
B130: ④借料 | C130: 1 | D130: ○ | H130: =IF(L130<=0,I130*J130,I130*J130*L130) -> 700000 | I130: 50000 | J130: 14 | K130: 日 | L130: 1 | M130: 回 | N130: ○○駅直結の駅型商業施設「■■」の場所代 ポッポアップストア開催（１４日間） | O130: 期間限定ショップ●● | P130: １２月 | Q130: ●●旅客鉄道株式会社
B131: ④借料 | C131: =C130+1 -> 2 | D131: ○ | H131: =IF(L131<=0,I131*J131,I131*J131*L131) -> 0
B132: ④借料 | C132: =C131+1 -> 3 | D132: ○ | H132: =IF(L132<=0,I132*J132,I132*J132*L132) -> 0
B133: ④借料 | C133: =C132+1 -> 4 | D133: ○ | H133: =IF(L133<=0,I133*J133,I133*J133*L133) -> 0
B134: ④借料 | C134: =C133+1 -> 5 | D134: ○ | H134: =IF(L134<=0,I134*J134,I134*J134*L134) -> 0
B135: ④借料 | C135: =C134+1 -> 6 | D135: ○ | H135: =IF(L135<=0,I135*J135,I135*J135*L135) -> 0
B136: ④借料 | C136: =C135+1 -> 7 | D136: ○ | H136: =IF(L136<=0,I136*J136,I136*J136*L136) -> 0
B137: ④借料 | C137: =C136+1 -> 8 | D137: ○ | H137: =IF(L137<=0,I137*J137,I137*J137*L137) -> 0
B138: ④借料 | C138: =C137+1 -> 9 | D138: ○ | H138: =IF(L138<=0,I138*J138,I138*J138*L138) -> 0
B139: ④借料 | C139: =C138+1 -> 10 | D139: ○ | H139: =IF(L139<=0,I139*J139,I139*J139*L139) -> 0
B140: ④借料 | C140: =C139+1 -> 11 | D140: ○ | H140: =IF(L140<=0,I140*J140,I140*J140*L140) -> 0
B141: ④借料 | C141: =C140+1 -> 12 | D141: ○ | H141: =IF(L141<=0,I141*J141,I141*J141*L141) -> 0
B142: ④借料 | C142: =C141+1 -> 13 | D142: ○ | H142: =IF(L142<=0,I142*J142,I142*J142*L142) -> 0
... B159: ④借料 | C159: =C158+1 -> 30 | D159: ○ | H159: =IF(L159<=0,I159*J159,I159*J159*L159) -> 0
B160: 合計 | H160: =SUM(H130:H159) -> 700000
B161: ⑤設営・設計費 （内外装費、整備工事等を含む） | C161: 1 | D161: ○ | H161: =IF(L161<=0,I161*J161,I161*J161*L161) -> 500000 | I161: 500000 | J161: 1 | K161: サイト | N161: ECサイト構費(初期費用) ●: サイト構築費（デザイン、開発費）、商品登録・撮影費(500,000円) | O161: ●●●オンラインストア | P161: １０月～１月 | Q161: ■◆株式会社
B162: ⑤設営・設計費 （内外装費、整備工事等を含む） | C162: =C161+1 -> 2 | D162: ○ | H162: =IF(L162<=0,I162*J162,I162*J162*L162) -> 500000 | I162: 100000 | J162: 5 | K162: カ月 | N162: ECサイト構費(ランニングコスト) ●システム利用料・月額費用: サーバー代、プラットフォーム利用料(100,000円×5カ月) | O162: ●●●オンラインストア | P162: ９月～１月 | Q162: ■◆株式会社
B163: ⑤設営・設計費 （内外装費、整備工事等を含む） | C163: =C162+1 -> 3 | D163: ○ | H163: =IF(L163<=0,I163*J163,I163*J163*L163) -> 450000 | I163: 450000 | J163: 1 | K163: 式 | N163: ■■展示会のブース施工・設備費 1式の内訳(壁、床、電気工事) | O163: ■■展示会 | P163: 11月 | Q163: ■■ジャパン株式会社
B164: ⑤設営・設計費 （内外装費、整備工事等を含む） | C164: =C163+1 -> 4 | D164: ○ | H164: =IF(L164<=0,I164*J164,I164*J164*L164) -> 250000 | I164: 250000 | J164: 1 | K164: 式 | N164: ■■展示会のブース装飾費 1式の内訳(デザイン、パネル、照明) | O164: ■■展示会 | P164: 11月 | Q164: ■■ジャパン株式会社
B165: ⑤設営・設計費 （内外装費、整備工事等を含む） | C165: =C164+1 -> 5 | D165: ○ | H165: =IF(L165<=0,I165*J165,I165*J165*L165) -> 0
B166: ⑤設営・設計費 （内外装費、整備工事等を含む） | C166: =C165+1 -> 6 | D166: ○ | H166: =IF(L166<=0,I166*J166,I166*J166*L166) -> 0
B167: ⑤設営・設計費 （内外装費、整備工事等を含む） | C167: =C166+1 -> 7 | D167: ○ | H167: =IF(L167<=0,I167*J167,I167*J167*L167) -> 0
B168: ⑤設営・設計費 （内外装費、整備工事等を含む） | C168: =C167+1 -> 8 | D168: ○ | H168: =IF(L168<=0,I168*J168,I168*J168*L168) -> 0
B169: ⑤設営・設計費 （内外装費、整備工事等を含む） | C169: =C168+1 -> 9 | D169: ○ | H169: =IF(L169<=0,I169*J169,I169*J169*L169) -> 0
B170: ⑤設営・設計費 （内外装費、整備工事等を含む） | C170: =C169+1 -> 10 | D170: ○ | H170: =IF(L170<=0,I170*J170,I170*J170*L170) -> 0
B171: ⑤設営・設計費 （内外装費、整備工事等を含む） | C171: =C170+1 -> 11 | D171: ○ | H171: =IF(L171<=0,I171*J171,I171*J171*L171) -> 0
B172: ⑤設営・設計費 （内外装費、整備工事等を含む） | C172: =C171+1 -> 12 | D172: ○ | H172: =IF(L172<=0,I172*J172,I172*J172*L172) -> 0
B173: ⑤設営・設計費 （内外装費、整備工事等を含む） | C173: =C172+1 -> 13 | D173: ○ | H173: =IF(L173<=0,I173*J173,I173*J173*L173) -> 0
B174: ⑤設営・設計費 （内外装費、整備工事等を含む） | C174: =C173+1 -> 14 | D174: ○ | H174: =IF(L174<=0,I174*J174,I174*J174*L174) -> 0
B175: ⑤設営・設計費 （内外装費、整備工事等を含む） | C175: =C174+1 -> 15 | D175: ○ | H175: =IF(L175<=0,I175*J175,I175*J175*L175) -> 0
B176: ⑤設営・設計費 （内外装費、整備工事等を含む） | C176: =C175+1 -> 16 | D176: ○ | H176: =IF(L176<=0,I176*J176,I176*J176*L176) -> 0
... B189: ⑤設営・設計費 （内外装費、整備工事等を含む） | C189: =C188+1 -> 29 | D189: ○ | H189: =IF(L189<=0,I189*J189,I189*J189*L189) -> 0
B190: ⑤設営・設計費 （内外装費、整備工事等を含む） | C190: =C189+1 -> 30 | D190: ○ | H190: =IF(L190<=0,I190*J190,I190*J190*L190) -> 0 | U190: ↓30行分を非表示にしています。使用する場合は再表示してください。
B191: ⑤設営・設計費 （内外装費、整備工事等を含む） | C191: =C190+1 -> 31 | D191: ○ | H191: =IF(L191<=0,I191*J191,I191*J191*L191) -> 0
...
